{
  "timestamp_utc": "2026-05-02T16:47:03.002058+00:00",
  "assets": {
    "BTC": {
      "kalshi": {
        "markets": [
          {
            "market": {
              "can_close_early": true,
              "close_time": "2026-05-02T17:00:00Z",
              "created_time": "2026-05-02T00:02:33.400434Z",
              "event_ticker": "KXBTC15M-26MAY021300",
              "expected_expiration_time": "2026-05-02T17:05:00Z",
              "expiration_time": "2026-05-09T17:00:00Z",
              "expiration_value": "",
              "floor_strike": 78452.16,
              "fractional_trading_enabled": true,
              "last_price_dollars": "0.4300",
              "latest_expiration_time": "2026-05-09T17:00:00Z",
              "liquidity_dollars": "0.0000",
              "market_type": "binary",
              "no_ask_dollars": "0.5800",
              "no_bid_dollars": "0.5700",
              "no_sub_title": "Target price: TBD",
              "notional_value_dollars": "1.0000",
              "occurrence_datetime": "2026-05-02T17:05:00Z",
              "open_interest_fp": "30716.78",
              "open_time": "2026-05-02T16:45:00Z",
              "previous_price_dollars": "0.0000",
              "previous_yes_ask_dollars": "0.0000",
              "previous_yes_bid_dollars": "0.0000",
              "price_level_structure": "tapered_deci_cent",
              "price_ranges": [
                {
                  "end": "0.1000",
                  "start": "0.0000",
                  "step": "0.0010"
                },
                {
                  "end": "0.9000",
                  "start": "0.1000",
                  "step": "0.0100"
                },
                {
                  "end": "1.0000",
                  "start": "0.9000",
                  "step": "0.0010"
                }
              ],
              "response_price_units": "usd_cent",
              "result": "",
              "rules_primary": "If the simple average of the sixty seconds of CF Benchmarks' BRTI before 1:00 PM EDT on May 2, 2026 is at least the simple average of the sixty seconds of CF Benchmarks' BRTI before 12:45 PM EDT on May 2, 2026, then the market resolves to Yes.",
              "rules_secondary": "Not all cryptocurrency price data is the same. While checking a source like Google or Coinbase may help guide your decision, the price used to determine this market is based on CF Benchmarks' corresponding Real Time Index (RTI). At the last minute before expiration, 60 RTI prices are collected. The official and final value is the average of these prices, rounded to the nearest 2 decimal places.",
              "settlement_timer_seconds": 1,
              "status": "active",
              "strike_type": "greater_or_equal",
              "tick_size": 1,
              "ticker": "KXBTC15M-26MAY021300-00",
              "title": "BTC price up in next 15 mins?",
              "updated_time": "2026-05-02T16:45:00.825445Z",
              "volume_24h_fp": "0.00",
              "volume_fp": "39399.32",
              "yes_ask_dollars": "0.4300",
              "yes_ask_size_fp": "3761.78",
              "yes_bid_dollars": "0.4200",
              "yes_bid_size_fp": "177.26",
              "yes_sub_title": "Target Price: $78,452.16"
            },
            "orderbook": null
          }
        ],
        "error": null
      },
      "kraken": {
        "price": 78426.5,
        "error": null
      },
      "coinbase": {
        "price": 78440.875,
        "error": null
      },
      "binance_us": {
        "price": 78429.16,
        "error": null
      },
      "kraken_funding": {
        "funding_rate": 0.009270442694484493,
        "funding_rate_prediction": -0.10494784959016312,
        "mark_price": 78427.88910141807,
        "index_price": 78428.79,
        "error": null
      }
    },
    "ETH": {
      "kalshi": {
        "markets": [
          {
            "market": {
              "can_close_early": true,
              "close_time": "2026-05-02T17:00:00Z",
              "created_time": "2026-05-02T00:02:33.496865Z",
              "event_ticker": "KXETH15M-26MAY021300",
              "expected_expiration_time": "2026-05-02T17:05:00Z",
              "expiration_time": "2026-05-09T17:00:00Z",
              "expiration_value": "",
              "floor_strike": 2308.41,
              "fractional_trading_enabled": true,
              "last_price_dollars": "0.5600",
              "latest_expiration_time": "2026-05-09T17:00:00Z",
              "liquidity_dollars": "0.0000",
              "market_type": "binary",
              "no_ask_dollars": "0.4600",
              "no_bid_dollars": "0.4500",
              "no_sub_title": "Target price: TBD",
              "notional_value_dollars": "1.0000",
              "occurrence_datetime": "2026-05-02T17:05:00Z",
              "open_interest_fp": "891.88",
              "open_time": "2026-05-02T16:45:00Z",
              "previous_price_dollars": "0.0000",
              "previous_yes_ask_dollars": "0.0000",
              "previous_yes_bid_dollars": "0.0000",
              "price_level_structure": "tapered_deci_cent",
              "price_ranges": [
                {
                  "end": "0.1000",
                  "start": "0.0000",
                  "step": "0.0010"
                },
                {
                  "end": "0.9000",
                  "start": "0.1000",
                  "step": "0.0100"
                },
                {
                  "end": "1.0000",
                  "start": "0.9000",
                  "step": "0.0010"
                }
              ],
              "response_price_units": "usd_cent",
              "result": "",
              "rules_primary": "If the simple average of the sixty seconds of CF Benchmarks' ETHUSDRTI before 1:00 PM EDT on May 2, 2026 is at least the simple average of the sixty seconds of CF Benchmarks' ETHUSDRTI before 12:45 PM EDT on May 2, 2026, then the market resolves to Yes.",
              "rules_secondary": "Not all cryptocurrency price data is the same. While checking a source like Google or Coinbase may help guide your decision, the price used to determine this market is based on CF Benchmarks' corresponding Real Time Index (RTI). At the last minute before expiration, 60 RTI prices are collected. The official and final value is the average of these prices, rounded to the nearest 2 decimal places.",
              "settlement_timer_seconds": 1,
              "status": "active",
              "strike_type": "greater_or_equal",
              "tick_size": 1,
              "ticker": "KXETH15M-26MAY021300-00",
              "title": "ETH price up in next 15 mins?",
              "updated_time": "2026-05-02T16:45:01.732095Z",
              "volume_24h_fp": "0.00",
              "volume_fp": "1143.45",
              "yes_ask_dollars": "0.5500",
              "yes_ask_size_fp": "930.14",
              "yes_bid_dollars": "0.5400",
              "yes_bid_size_fp": "2.00",
              "yes_sub_title": "Target Price: $2,308.41"
            },
            "orderbook": null
          }
        ],
        "error": null
      },
      "kraken": {
        "price": 2307.88,
        "error": null
      },
      "coinbase": {
        "price": 2308.525,
        "error": null
      },
      "binance_us": {
        "price": 2309.42,
        "error": null
      },
      "kraken_funding": {
        "funding_rate": 0.010342252250556582,
        "funding_rate_prediction": 0.009137161203264145,
        "mark_price": 2308.24201231061,
        "index_price": 2308.02,
        "error": null
      }
    },
    "SOL": {
      "kalshi": {
        "markets": [
          {
            "market": {
              "can_close_early": true,
              "close_time": "2026-05-02T17:00:00Z",
              "created_time": "2026-05-02T00:02:31.218967Z",
              "event_ticker": "KXSOL15M-26MAY021300",
              "expected_expiration_time": "2026-05-02T17:05:00Z",
              "expiration_time": "2026-05-09T17:00:00Z",
              "expiration_value": "",
              "floor_strike": 84.1138,
              "fractional_trading_enabled": true,
              "last_price_dollars": "0.3700",
              "latest_expiration_time": "2026-05-09T17:00:00Z",
              "liquidity_dollars": "0.0000",
              "market_type": "binary",
              "no_ask_dollars": "0.6700",
              "no_bid_dollars": "0.6100",
              "no_sub_title": "Target price: TBD",
              "notional_value_dollars": "1.0000",
              "occurrence_datetime": "2026-05-02T17:05:00Z",
              "open_interest_fp": "108.42",
              "open_time": "2026-05-02T16:45:00Z",
              "previous_price_dollars": "0.0000",
              "previous_yes_ask_dollars": "0.0000",
              "previous_yes_bid_dollars": "0.0000",
              "price_level_structure": "tapered_deci_cent",
              "price_ranges": [
                {
                  "end": "0.1000",
                  "start": "0.0000",
                  "step": "0.0010"
                },
                {
                  "end": "0.9000",
                  "start": "0.1000",
                  "step": "0.0100"
                },
                {
                  "end": "1.0000",
                  "start": "0.9000",
                  "step": "0.0010"
                }
              ],
              "response_price_units": "usd_cent",
              "result": "",
              "rules_primary": "If the simple average of the sixty seconds of CF Benchmarks' SOLUSDRTI before 1:00 PM EDT on May 2, 2026 is at least the simple average of the sixty seconds of CF Benchmarks' SOLUSDRTI before 12:45 PM EDT on May 2, 2026, then the market resolves to Yes.",
              "rules_secondary": "Not all cryptocurrency price data is the same. While checking a source like Google or Coinbase may help guide your decision, the price used to determine this market is based on CF Benchmarks' corresponding Real Time Index (RTI). At the last minute before expiration, 60 RTI prices are collected. The official and final value is the average of these prices, rounded to the nearest 4 decimal places.",
              "settlement_timer_seconds": 1,
              "status": "active",
              "strike_type": "greater_or_equal",
              "tick_size": 1,
              "ticker": "KXSOL15M-26MAY021300-00",
              "title": "SOL price up in next 15 mins?",
              "updated_time": "2026-05-02T16:45:02.395074Z",
              "volume_24h_fp": "0.00",
              "volume_fp": "124.42",
              "yes_ask_dollars": "0.3900",
              "yes_ask_size_fp": "13.00",
              "yes_bid_dollars": "0.3300",
              "yes_bid_size_fp": "4.00",
              "yes_sub_title": "Target Price: $84.1138"
            },
            "orderbook": null
          }
        ],
        "error": null
      },
      "kraken": {
        "price": 84.1,
        "error": null
      },
      "coinbase": {
        "price": 84.09,
        "error": null
      },
      "binance_us": {
        "price": 84.12,
        "error": null
      },
      "kraken_funding": {
        "funding_rate": 0.000541936025180565,
        "funding_rate_prediction": 0.000159692516000028,
        "mark_price": 84.11068622739,
        "index_price": 84.12,
        "error": null
      }
    },
    "XRP": {
      "kalshi": {
        "markets": [
          {
            "market": {
              "can_close_early": true,
              "close_time": "2026-05-02T17:00:00Z",
              "created_time": "2026-05-02T00:02:33.133529Z",
              "event_ticker": "KXXRP15M-26MAY021300",
              "expected_expiration_time": "2026-05-02T17:05:00Z",
              "expiration_time": "2026-05-09T17:00:00Z",
              "expiration_value": "",
              "floor_strike": 1.3916,
              "fractional_trading_enabled": true,
              "last_price_dollars": "0.5900",
              "latest_expiration_time": "2026-05-09T17:00:00Z",
              "liquidity_dollars": "0.0000",
              "market_type": "binary",
              "no_ask_dollars": "0.4500",
              "no_bid_dollars": "0.4300",
              "no_sub_title": "Target price: TBD",
              "notional_value_dollars": "1.0000",
              "occurrence_datetime": "2026-05-02T17:05:00Z",
              "open_interest_fp": "55.35",
              "open_time": "2026-05-02T16:45:00Z",
              "previous_price_dollars": "0.0000",
              "previous_yes_ask_dollars": "0.0000",
              "previous_yes_bid_dollars": "0.0000",
              "price_level_structure": "tapered_deci_cent",
              "price_ranges": [
                {
                  "end": "0.1000",
                  "start": "0.0000",
                  "step": "0.0010"
                },
                {
                  "end": "0.9000",
                  "start": "0.1000",
                  "step": "0.0100"
                },
                {
                  "end": "1.0000",
                  "start": "0.9000",
                  "step": "0.0010"
                }
              ],
              "response_price_units": "usd_cent",
              "result": "",
              "rules_primary": "If the simple average of the sixty seconds of CF Benchmarks' XRPUSDRTI before 1:00 PM EDT on May 2, 2026 is at least the simple average of the sixty seconds of CF Benchmarks' XRPUSDRTI before 12:45 PM EDT on May 2, 2026, then the market resolves to Yes.",
              "rules_secondary": "Not all cryptocurrency price data is the same. While checking a source like Google or Coinbase may help guide your decision, the price used to determine this market is based on CF Benchmarks' corresponding Real Time Index (RTI). At the last minute before expiration, 60 RTI prices are collected. The official and final value is the average of these prices, rounded to the nearest 4 decimal places.",
              "settlement_timer_seconds": 1,
              "status": "active",
              "strike_type": "greater_or_equal",
              "tick_size": 1,
              "ticker": "KXXRP15M-26MAY021300-00",
              "title": "XRP price up in next 15 mins?",
              "updated_time": "2026-05-02T16:45:03.07976Z",
              "volume_24h_fp": "0.00",
              "volume_fp": "58.35",
              "yes_ask_dollars": "0.5700",
              "yes_ask_size_fp": "1.55",
              "yes_bid_dollars": "0.5500",
              "yes_bid_size_fp": "2.00",
              "yes_sub_title": "Target Price: $1.3916"
            },
            "orderbook": null
          }
        ],
        "error": null
      },
      "kraken": {
        "price": 1.39149,
        "error": null
      },
      "coinbase": {
        "price": 1.39155,
        "error": null
      },
      "binance_us": {
        "price": 1.3919,
        "error": null
      },
      "kraken_funding": {
        "funding_rate": -6.079231954875e-06,
        "funding_rate_prediction": -6.046633354527e-06,
        "mark_price": 1.39134829934,
        "index_price": 1.39158,
        "error": null
      }
    },
    "DOGE": {
      "kalshi": {
        "markets": [
          {
            "market": {
              "can_close_early": true,
              "close_time": "2026-05-02T17:00:00Z",
              "created_time": "2026-05-02T00:02:33.081358Z",
              "event_ticker": "KXDOGE15M-26MAY021300",
              "expected_expiration_time": "2026-05-02T17:05:00Z",
              "expiration_time": "2026-05-09T17:00:00Z",
              "expiration_value": "",
              "floor_strike": 0.1089,
              "fractional_trading_enabled": true,
              "last_price_dollars": "0.4700",
              "latest_expiration_time": "2026-05-09T17:00:00Z",
              "liquidity_dollars": "0.0000",
              "market_type": "binary",
              "no_ask_dollars": "0.5300",
              "no_bid_dollars": "0.4200",
              "no_sub_title": "Target price: TBD",
              "notional_value_dollars": "1.0000",
              "occurrence_datetime": "2026-05-02T17:05:00Z",
              "open_interest_fp": "6.82",
              "open_time": "2026-05-02T16:45:00Z",
              "previous_price_dollars": "0.0000",
              "previous_yes_ask_dollars": "0.0000",
              "previous_yes_bid_dollars": "0.0000",
              "price_level_structure": "tapered_deci_cent",
              "price_ranges": [
                {
                  "end": "0.1000",
                  "start": "0.0000",
                  "step": "0.0010"
                },
                {
                  "end": "0.9000",
                  "start": "0.1000",
                  "step": "0.0100"
                },
                {
                  "end": "1.0000",
                  "start": "0.9000",
                  "step": "0.0010"
                }
              ],
              "response_price_units": "usd_cent",
              "result": "",
              "rules_primary": "If the simple average of the sixty seconds of CF Benchmarks' DOGEUSDRTI before 1:00 PM EDT on May 2, 2026 is at least the simple average of the sixty seconds of CF Benchmarks' DOGEUSDRTI before 12:45 PM EDT on May 2, 2026, then the market resolves to Yes.",
              "rules_secondary": "Not all cryptocurrency price data is the same. While checking a source like Google or Coinbase may help guide your decision, the price used to determine this market is based on CF Benchmarks' corresponding Real Time Index (RTI). At the last minute before expiration, 60 RTI prices are collected. The official and final value is the average of these prices, rounded to the nearest 7 decimal places.",
              "settlement_timer_seconds": 1,
              "status": "active",
              "strike_type": "greater_or_equal",
              "tick_size": 1,
              "ticker": "KXDOGE15M-26MAY021300-00",
              "title": "DOGE price up in next 15 mins?",
              "updated_time": "2026-05-02T16:45:04.442204Z",
              "volume_24h_fp": "0.00",
              "volume_fp": "6.82",
              "yes_ask_dollars": "0.5800",
              "yes_ask_size_fp": "5.00",
              "yes_bid_dollars": "0.4700",
              "yes_bid_size_fp": "5.18",
              "yes_sub_title": "Target Price: $0.1089004"
            },
            "orderbook": null
          }
        ],
        "error": null
      },
      "kraken": {
        "price": 0.1089032,
        "error": null
      },
      "coinbase": {
        "price": 0.108895,
        "error": null
      },
      "binance_us": {
        "price": 0.10896,
        "error": null
      },
      "kraken_funding": {
        "funding_rate": -4.564690277e-07,
        "funding_rate_prediction": -2.35442110547e-07,
        "mark_price": 0.10890968847,
        "index_price": 0.108913,
        "error": null
      }
    }
  }
}