{
  "generated_at": "2026-05-01T20:47:15.064047Z",
  "n_matched_predictions": 4437,
  "note": "Raw signal analysis tests each individual signal's predictive power. Older predictions logged before raw signals were captured will show lower n. funding_rate signal is brand new \u2014 needs significant data accumulation before its results are meaningful.",
  "raw_signals": {
    "momentum_short": {
      "signal": "momentum_short",
      "n": 3808,
      "signal_mean": -0.004,
      "signal_stdev": 0.9306,
      "mean_when_yes": 0.1914,
      "mean_when_no": -0.2052,
      "separation": 0.3966,
      "correlation_with_outcome": 0.2131,
      "predict_alone_accuracy_threshold_0": 0.5882,
      "best_threshold_found": 0.0,
      "best_accuracy_with_threshold": 0.5882,
      "confusion_at_zero": {
        "true_yes": 1132,
        "false_yes": 768,
        "true_no": 1108,
        "false_no": 800
      }
    },
    "momentum_medium": {
      "signal": "momentum_medium",
      "n": 3808,
      "signal_mean": -0.0053,
      "signal_stdev": 2.2865,
      "mean_when_yes": 0.8846,
      "mean_when_no": -0.9218,
      "separation": 1.8064,
      "correlation_with_outcome": 0.395,
      "predict_alone_accuracy_threshold_0": 0.683,
      "best_threshold_found": -0.0314,
      "best_accuracy_with_threshold": 0.6841,
      "confusion_at_zero": {
        "true_yes": 1295,
        "false_yes": 570,
        "true_no": 1306,
        "false_no": 637
      }
    },
    "trend_slope": {
      "signal": "trend_slope",
      "n": 3808,
      "signal_mean": -0.0242,
      "signal_stdev": 0.5176,
      "mean_when_yes": 0.1335,
      "mean_when_no": -0.1865,
      "separation": 0.32,
      "correlation_with_outcome": 0.3091,
      "predict_alone_accuracy_threshold_0": 0.6352,
      "best_threshold_found": 0.0,
      "best_accuracy_with_threshold": 0.6352,
      "confusion_at_zero": {
        "true_yes": 1194,
        "false_yes": 651,
        "true_no": 1225,
        "false_no": 738
      }
    },
    "exchange_alignment": {
      "signal": "exchange_alignment",
      "n": 3808,
      "signal_mean": -0.1176,
      "signal_stdev": 0.9581,
      "mean_when_yes": 0.0451,
      "mean_when_no": -0.2852,
      "separation": 0.3303,
      "correlation_with_outcome": 0.1724,
      "predict_alone_accuracy_threshold_0": 0.5657,
      "best_threshold_found": 0.0,
      "best_accuracy_with_threshold": 0.5657,
      "confusion_at_zero": {
        "true_yes": 836,
        "false_yes": 558,
        "true_no": 1318,
        "false_no": 1096
      }
    },
    "distance_from_strike": {
      "signal": "distance_from_strike",
      "n": 3808,
      "signal_mean": 0.1785,
      "signal_stdev": 5.3344,
      "mean_when_yes": 3.1055,
      "mean_when_no": -2.8359,
      "separation": 5.9414,
      "correlation_with_outcome": 0.5569,
      "predict_alone_accuracy_threshold_0": 0.8078,
      "best_threshold_found": 0.0832,
      "best_accuracy_with_threshold": 0.8086,
      "confusion_at_zero": {
        "true_yes": 1573,
        "false_yes": 373,
        "true_no": 1503,
        "false_no": 359
      }
    },
    "funding_rate": {
      "signal": "funding_rate",
      "n": 3793,
      "signal_mean": 0.1846,
      "signal_stdev": 5.5892,
      "mean_when_yes": 0.1452,
      "mean_when_no": 0.2251,
      "separation": -0.0799,
      "correlation_with_outcome": -0.0071,
      "predict_alone_accuracy_threshold_0": 0.521,
      "best_threshold_found": 0.0,
      "best_accuracy_with_threshold": 0.521,
      "confusion_at_zero": {
        "true_yes": 987,
        "false_yes": 884,
        "true_no": 989,
        "false_no": 933
      }
    }
  },
  "derived_signals": {
    "our_prob_minus_0.5": {
      "signal": "our_prob_minus_0.5",
      "n": 4437,
      "signal_mean": -0.0044,
      "signal_stdev": 0.2844,
      "mean_when_yes": 0.178,
      "mean_when_no": -0.1879,
      "separation": 0.3659,
      "correlation_with_outcome": 0.6434,
      "predict_alone_accuracy_threshold_0": 0.7818,
      "best_threshold_found": -0.007,
      "best_accuracy_with_threshold": 0.7841,
      "confusion_at_zero": {
        "true_yes": 1719,
        "false_yes": 462,
        "true_no": 1750,
        "false_no": 506
      }
    },
    "market_mid_minus_0.5": {
      "signal": "market_mid_minus_0.5",
      "n": 4437,
      "signal_mean": -0.0134,
      "signal_stdev": 0.3195,
      "mean_when_yes": 0.1998,
      "mean_when_no": -0.2279,
      "separation": 0.4277,
      "correlation_with_outcome": 0.6694,
      "predict_alone_accuracy_threshold_0": 0.7942,
      "best_threshold_found": -0.015,
      "best_accuracy_with_threshold": 0.7956,
      "confusion_at_zero": {
        "true_yes": 1711,
        "false_yes": 399,
        "true_no": 1813,
        "false_no": 514
      }
    },
    "disagreement": {
      "signal": "disagreement",
      "n": 4437,
      "signal_mean": 0.009,
      "signal_stdev": 0.1356,
      "mean_when_yes": -0.0218,
      "mean_when_no": 0.0399,
      "separation": -0.0618,
      "correlation_with_outcome": -0.2279,
      "predict_alone_accuracy_threshold_0": 0.3692,
      "best_threshold_found": 0.093,
      "best_accuracy_with_threshold": 0.426,
      "confusion_at_zero": {
        "true_yes": 881,
        "false_yes": 1455,
        "true_no": 757,
        "false_no": 1344
      }
    },
    "prob_strength": {
      "signal": "prob_strength",
      "n": 4437,
      "signal_mean": 0.2495,
      "signal_stdev": 0.1364,
      "mean_when_yes": 0.2463,
      "mean_when_no": 0.2528,
      "separation": -0.0065,
      "correlation_with_outcome": -0.0238,
      "predict_alone_accuracy_threshold_0": 0.5012,
      "best_threshold_found": 0.0,
      "best_accuracy_with_threshold": 0.5012,
      "confusion_at_zero": {
        "true_yes": 2223,
        "false_yes": 2211,
        "true_no": 1,
        "false_no": 2
      }
    },
    "confidence": {
      "signal": "confidence",
      "n": 4437,
      "signal_mean": 0.9339,
      "signal_stdev": 0.1285,
      "mean_when_yes": 0.9504,
      "mean_when_no": 0.9172,
      "separation": 0.0332,
      "correlation_with_outcome": 0.1293,
      "predict_alone_accuracy_threshold_0": 0.5015,
      "best_threshold_found": 0.0,
      "best_accuracy_with_threshold": 0.5015,
      "confusion_at_zero": {
        "true_yes": 2225,
        "false_yes": 2212,
        "true_no": 0,
        "false_no": 0
      }
    }
  },
  "losses_vs_wins_when_confident": {
    "n_confident_predictions": 2752,
    "n_wins": 2446,
    "n_losses": 306,
    "win_rate_when_confident": 0.889,
    "mean_disagreement_in_losses": 0.0137,
    "mean_disagreement_in_wins": 0.0089,
    "mean_seconds_left_in_losses": 546.2,
    "mean_seconds_left_in_wins": 343.1
  },
  "by_phase": {
    "very_early (>=10min)": {
      "n_total": 947,
      "n_confident": 418,
      "win_rate_when_confident": 0.737,
      "our_brier": 0.2226,
      "market_brier": 0.2099,
      "we_beat_market": false
    },
    "early (5-10min)": {
      "n_total": 1720,
      "n_confident": 1030,
      "win_rate_when_confident": 0.857,
      "our_brier": 0.1683,
      "market_brier": 0.1635,
      "we_beat_market": false
    },
    "mid (2-5min)": {
      "n_total": 998,
      "n_confident": 708,
      "win_rate_when_confident": 0.939,
      "our_brier": 0.1072,
      "market_brier": 0.0972,
      "we_beat_market": false
    },
    "final_minute (<60s)": {
      "n_total": 772,
      "n_confident": 596,
      "win_rate_when_confident": 0.99,
      "our_brier": 0.0636,
      "market_brier": 0.0481,
      "we_beat_market": false
    }
  },
  "by_asset": {
    "ETH": {
      "n_total": 912,
      "n_confident": 574,
      "win_rate_when_confident": 0.883,
      "our_brier": 0.15,
      "market_brier": 0.1401,
      "we_beat_market": false
    },
    "DOGE": {
      "n_total": 838,
      "n_confident": 577,
      "win_rate_when_confident": 0.894,
      "our_brier": 0.1399,
      "market_brier": 0.1317,
      "we_beat_market": false
    },
    "XRP": {
      "n_total": 885,
      "n_confident": 537,
      "win_rate_when_confident": 0.896,
      "our_brier": 0.1431,
      "market_brier": 0.1344,
      "we_beat_market": false
    },
    "SOL": {
      "n_total": 878,
      "n_confident": 529,
      "win_rate_when_confident": 0.9,
      "our_brier": 0.1484,
      "market_brier": 0.1429,
      "we_beat_market": false
    },
    "BTC": {
      "n_total": 924,
      "n_confident": 535,
      "win_rate_when_confident": 0.871,
      "our_brier": 0.1574,
      "market_brier": 0.1424,
      "we_beat_market": false
    }
  }
}